auto_shap/__init__.py
auto_shap/auto_shap.py
auto_shap/config.py
auto_shap/scratch.py
auto_shap/utilities.py
auto_shap-0.1.1.dist-info/LICENSE.txt
auto_shap-0.1.1.dist-info/METADATA
auto_shap-0.1.1.dist-info/WHEEL
auto_shap-0.1.1.dist-info/top_level.txt
auto_shap-0.1.1.dist-info/RECORD
