Metadata-Version: 2.1
Name: auto-shap
Version: 0.1.1
Summary: Calculate SHAP values in parallel and automatically detect what explainer to use
Home-page: https://github.com/micahmelling/auto-shap
Author: Micah Melling
Author-email: micahmelling@gmail.com
License: MIT
Platform: UNKNOWN
Classifier: Programming Language :: Python :: 3
Classifier: License :: OSI Approved :: MIT License
Classifier: Operating System :: OS Independent
Requires-Python: >=3.6
Requires-Dist: shap (>=0.35.0)
Requires-Dist: pandas (>=1.1.5)
Requires-Dist: numpy (>=1.19.4)
Requires-Dist: matplotlib (>=3.2.0)
